etc/klemmbrett.conf
etc/xdg/autostart/klemmbrett-autostart.desktop
klemmbrett/__init__.py
klemmbrett/about.py
klemmbrett/config.py
klemmbrett/util.py
klemmbrett/assets/klemmbrett.png
klemmbrett/callable/__init__.py
klemmbrett/callable/alchemy.py
klemmbrett/plugins/__init__.py
klemmbrett/plugins/dbus_service.py
klemmbrett/plugins/exchange.py
klemmbrett/plugins/ubuntu.py
klemmbrett-0.3.3.data/data/share/klemmbrett/gtk-paste.svg
klemmbrett-0.3.3.data/data/share/klemmbrett/gtk-paste2.svg
klemmbrett-0.3.3.data/scripts/klemmbrett
klemmbrett-0.3.3.dist-info/LICENSE.txt
klemmbrett-0.3.3.dist-info/METADATA
klemmbrett-0.3.3.dist-info/WHEEL
klemmbrett-0.3.3.dist-info/top_level.txt
klemmbrett-0.3.3.dist-info/RECORD
