Metadata-Version: 2.1
Name: klemmbrett
Version: 0.3.3
Summary: Versatile clipboard manager
Home-page: https://github.com/wontfix-org/klemmbrett
Author: Michael van Bracht
Author-email: michael@wontfix.org
License: MIT
Platform: UNKNOWN
Classifier: Programming Language :: Python :: 3 :: Only
Classifier: Environment :: X11 Applications :: GTK
Requires-Dist: notify2
Requires-Dist: dbus-python
Requires-Dist: pygobject
Requires-Dist: pycrypto
